<Map background-color="#f2efe9" srs="+proj=merc +a=6378137 +b=6378137 +lat_ts=0.0 +lon_0=0.0 +x_0=0.0 +y_0=0.0 +k=1.0 +units=m +nadgrids=@null +wktext +no_defs +over">
  <Parameters>
    <Parameter name="scale">1</Parameter>
    <Parameter name="metatile">2</Parameter>
    <Parameter name="name"><![CDATA[OpenStreetMap Carto]]></Parameter>
    <Parameter name="description"><![CDATA[A general-purpose OpenStreetMap mapnik style, in CartoCSS]]></Parameter>
    <Parameter name="bounds">-180,-85.05112877980659,180,85.05112877980659</Parameter>
    <Parameter name="center">0,0,4</Parameter>
    <Parameter name="format"><![CDATA[png]]></Parameter>
    <Parameter name="minzoom">0</Parameter>
    <Parameter name="maxzoom">22</Parameter>
  </Parameters>
  <FontSet name="fontset-0">
    <Font face-name="Noto Sans Regular" />
    <Font face-name="Noto Sans CJK JP Regular" />
    <Font face-name="Noto Sans Adlam Regular" />
    <Font face-name="Noto Sans Adlam Unjoined Regular" />
    <Font face-name="Noto Sans Armenian Regular" />
    <Font face-name="Noto Sans Balinese Regular" />
    <Font face-name="Noto Sans Bamum Regular" />
    <Font face-name="Noto Sans Batak Regular" />
    <Font face-name="Noto Sans Bengali UI Regular" />
    <Font face-name="Noto Sans Buginese Regular" />
    <Font face-name="Noto Sans Buhid Regular" />
    <Font face-name="Noto Sans Canadian Aboriginal Regular" />
    <Font face-name="Noto Sans Chakma Regular" />
    <Font face-name="Noto Sans Cham Regular" />
    <Font face-name="Noto Sans Cherokee Regular" />
    <Font face-name="Noto Sans Coptic Regular" />
    <Font face-name="Noto Sans Devanagari UI Regular" />
    <Font face-name="Noto Sans Ethiopic Regular" />
    <Font face-name="Noto Sans Georgian Regular" />
    <Font face-name="Noto Sans Gujarati UI Regular" />
    <Font face-name="Noto Sans Gurmukhi UI Regular" />
    <Font face-name="Noto Sans Hanunoo Regular" />
    <Font face-name="Noto Sans Hebrew Regular" />
    <Font face-name="Noto Sans Javanese Regular" />
    <Font face-name="Noto Sans Kannada UI Regular" />
    <Font face-name="Noto Sans Kayah Li Regular" />
    <Font face-name="Noto Sans Khmer UI Regular" />
    <Font face-name="Noto Sans Lao UI Regular" />
    <Font face-name="Noto Sans Lepcha Regular" />
    <Font face-name="Noto Sans Limbu Regular" />
    <Font face-name="Noto Sans Lisu Regular" />
    <Font face-name="Noto Sans Malayalam UI Regular" />
    <Font face-name="Noto Sans Mandaic Regular" />
    <Font face-name="Noto Sans Mongolian Regular" />
    <Font face-name="Noto Sans Myanmar UI Regular" />
    <Font face-name="Noto Sans New Tai Lue Regular" />
    <Font face-name="Noto Sans NKo Regular" />
    <Font face-name="Noto Sans Ol Chiki Regular" />
    <Font face-name="Noto Sans Oriya UI Regular" />
    <Font face-name="Noto Sans Osage Regular" />
    <Font face-name="Noto Sans Osmanya Regular" />
    <Font face-name="Noto Sans Samaritan Regular" />
    <Font face-name="Noto Sans Saurashtra Regular" />
    <Font face-name="Noto Sans Shavian Regular" />
    <Font face-name="Noto Sans Sinhala UI Regular" />
    <Font face-name="Noto Sans Sinhala Regular" />
    <Font face-name="Noto Sans Sundanese Regular" />
    <Font face-name="Noto Sans Symbols Regular" />
    <Font face-name="Noto Sans Symbols2 Regular" />
    <Font face-name="Noto Sans Syriac Regular" />
    <Font face-name="Noto Sans Tagalog Regular" />
    <Font face-name="Noto Sans Tagbanwa Regular" />
    <Font face-name="Noto Sans Tai Le Regular" />
    <Font face-name="Noto Sans Tai Tham Regular" />
    <Font face-name="Noto Sans Tai Viet Regular" />
    <Font face-name="Noto Sans Tamil UI Regular" />
    <Font face-name="Noto Sans Telugu UI Regular" />
    <Font face-name="Noto Sans Thaana Regular" />
    <Font face-name="Noto Sans Thai UI Regular" />
    <Font face-name="Noto Sans Tifinagh Regular" />
    <Font face-name="Noto Sans Vai Regular" />
    <Font face-name="Noto Sans Yi Regular" />
    <Font face-name="Noto Sans Arabic UI Regular" />
    <Font face-name="Noto Naskh Arabic UI Regular" />
    <Font face-name="Noto Serif Tibetan Regular" />
    <Font face-name="Noto Emoji Regular" />
    <Font face-name="DejaVu Sans Book" />
    <Font face-name="HanaMinA Regular" />
    <Font face-name="HanaMinB Regular" />
    <Font face-name="Unifont Medium" />
  </FontSet>
  <FontSet name="fontset-1">
    <Font face-name="Noto Sans Italic" />
    <Font face-name="Noto Sans Regular" />
    <Font face-name="Noto Sans CJK JP Regular" />
    <Font face-name="Noto Sans Adlam Regular" />
    <Font face-name="Noto Sans Adlam Unjoined Regular" />
    <Font face-name="Noto Sans Armenian Regular" />
    <Font face-name="Noto Sans Balinese Regular" />
    <Font face-name="Noto Sans Bamum Regular" />
    <Font face-name="Noto Sans Batak Regular" />
    <Font face-name="Noto Sans Bengali UI Regular" />
    <Font face-name="Noto Sans Buginese Regular" />
    <Font face-name="Noto Sans Buhid Regular" />
    <Font face-name="Noto Sans Canadian Aboriginal Regular" />
    <Font face-name="Noto Sans Chakma Regular" />
    <Font face-name="Noto Sans Cham Regular" />
    <Font face-name="Noto Sans Cherokee Regular" />
    <Font face-name="Noto Sans Coptic Regular" />
    <Font face-name="Noto Sans Devanagari UI Regular" />
    <Font face-name="Noto Sans Ethiopic Regular" />
    <Font face-name="Noto Sans Georgian Regular" />
    <Font face-name="Noto Sans Gujarati UI Regular" />
    <Font face-name="Noto Sans Gurmukhi UI Regular" />
    <Font face-name="Noto Sans Hanunoo Regular" />
    <Font face-name="Noto Sans Hebrew Regular" />
    <Font face-name="Noto Sans Javanese Regular" />
    <Font face-name="Noto Sans Kannada UI Regular" />
    <Font face-name="Noto Sans Kayah Li Regular" />
    <Font face-name="Noto Sans Khmer UI Regular" />
    <Font face-name="Noto Sans Lao UI Regular" />
    <Font face-name="Noto Sans Lepcha Regular" />
    <Font face-name="Noto Sans Limbu Regular" />
    <Font face-name="Noto Sans Lisu Regular" />
    <Font face-name="Noto Sans Malayalam UI Regular" />
    <Font face-name="Noto Sans Mandaic Regular" />
    <Font face-name="Noto Sans Mongolian Regular" />
    <Font face-name="Noto Sans Myanmar UI Regular" />
    <Font face-name="Noto Sans New Tai Lue Regular" />
    <Font face-name="Noto Sans NKo Regular" />
    <Font face-name="Noto Sans Ol Chiki Regular" />
    <Font face-name="Noto Sans Oriya UI Regular" />
    <Font face-name="Noto Sans Osage Regular" />
    <Font face-name="Noto Sans Osmanya Regular" />
    <Font face-name="Noto Sans Samaritan Regular" />
    <Font face-name="Noto Sans Saurashtra Regular" />
    <Font face-name="Noto Sans Shavian Regular" />
    <Font face-name="Noto Sans Sinhala UI Regular" />
    <Font face-name="Noto Sans Sinhala Regular" />
    <Font face-name="Noto Sans Sundanese Regular" />
    <Font face-name="Noto Sans Symbols Regular" />
    <Font face-name="Noto Sans Symbols2 Regular" />
    <Font face-name="Noto Sans Syriac Regular" />
    <Font face-name="Noto Sans Tagalog Regular" />
    <Font face-name="Noto Sans Tagbanwa Regular" />
    <Font face-name="Noto Sans Tai Le Regular" />
    <Font face-name="Noto Sans Tai Tham Regular" />
    <Font face-name="Noto Sans Tai Viet Regular" />
    <Font face-name="Noto Sans Tamil UI Regular" />
    <Font face-name="Noto Sans Telugu UI Regular" />
    <Font face-name="Noto Sans Thaana Regular" />
    <Font face-name="Noto Sans Thai UI Regular" />
    <Font face-name="Noto Sans Tifinagh Regular" />
    <Font face-name="Noto Sans Vai Regular" />
    <Font face-name="Noto Sans Yi Regular" />
    <Font face-name="Noto Sans Arabic UI Regular" />
    <Font face-name="Noto Naskh Arabic UI Regular" />
    <Font face-name="Noto Serif Tibetan Regular" />
    <Font face-name="Noto Emoji Regular" />
    <Font face-name="DejaVu Sans Book" />
    <Font face-name="HanaMinA Regular" />
    <Font face-name="HanaMinB Regular" />
    <Font face-name="Unifont Medium" />
  </FontSet>
  <FontSet name="fontset-2">
    <Font face-name="Noto Sans Bold" />
    <Font face-name="Noto Sans CJK JP Bold" />
    <Font face-name="Noto Sans Armenian Bold" />
    <Font face-name="Noto Sans Bengali UI Bold" />
    <Font face-name="Noto Sans Cham Bold" />
    <Font face-name="Noto Sans Cherokee Bold" />
    <Font face-name="Noto Sans Devanagari UI Bold" />
    <Font face-name="Noto Sans Ethiopic Bold" />
    <Font face-name="Noto Sans Georgian Bold" />
    <Font face-name="Noto Sans Gujarati UI Bold" />
    <Font face-name="Noto Sans Gurmukhi UI Bold" />
    <Font face-name="Noto Sans Hebrew Bold" />
    <Font face-name="Noto Sans Kannada UI Bold" />
    <Font face-name="Noto Sans Khmer UI Bold" />
    <Font face-name="Noto Sans Lao UI Bold" />
    <Font face-name="Noto Sans Malayalam UI Bold" />
    <Font face-name="Noto Sans Myanmar UI Bold" />
    <Font face-name="Noto Sans Oriya UI Bold" />
    <Font face-name="Noto Sans Sinhala UI Bold" />
    <Font face-name="Noto Sans Sinhala Bold" />
    <Font face-name="Noto Sans Symbols Bold" />
    <Font face-name="Noto Sans Tamil UI Bold" />
    <Font face-name="Noto Sans Telugu UI Bold" />
    <Font face-name="Noto Sans Thaana Bold" />
    <Font face-name="Noto Sans Thai UI Bold" />
    <Font face-name="Noto Sans Arabic UI Bold" />
    <Font face-name="Noto Naskh Arabic UI Bold" />
    <Font face-name="Noto Serif Tibetan Bold" />
    <Font face-name="DejaVu Sans Bold" />
    <Font face-name="Noto Sans Regular" />
    <Font face-name="Noto Sans CJK JP Regular" />
    <Font face-name="Noto Sans Adlam Regular" />
    <Font face-name="Noto Sans Adlam Unjoined Regular" />
    <Font face-name="Noto Sans Armenian Regular" />
    <Font face-name="Noto Sans Balinese Regular" />
    <Font face-name="Noto Sans Bamum Regular" />
    <Font face-name="Noto Sans Batak Regular" />
    <Font face-name="Noto Sans Bengali UI Regular" />
    <Font face-name="Noto Sans Buginese Regular" />
    <Font face-name="Noto Sans Buhid Regular" />
    <Font face-name="Noto Sans Canadian Aboriginal Regular" />
    <Font face-name="Noto Sans Chakma Regular" />
    <Font face-name="Noto Sans Cham Regular" />
    <Font face-name="Noto Sans Cherokee Regular" />
    <Font face-name="Noto Sans Coptic Regular" />
    <Font face-name="Noto Sans Devanagari UI Regular" />
    <Font face-name="Noto Sans Ethiopic Regular" />
    <Font face-name="Noto Sans Georgian Regular" />
    <Font face-name="Noto Sans Gujarati UI Regular" />
    <Font face-name="Noto Sans Gurmukhi UI Regular" />
    <Font face-name="Noto Sans Hanunoo Regular" />
    <Font face-name="Noto Sans Hebrew Regular" />
    <Font face-name="Noto Sans Javanese Regular" />
    <Font face-name="Noto Sans Kannada UI Regular" />
    <Font face-name="Noto Sans Kayah Li Regular" />
    <Font face-name="Noto Sans Khmer UI Regular" />
    <Font face-name="Noto Sans Lao UI Regular" />
    <Font face-name="Noto Sans Lepcha Regular" />
    <Font face-name="Noto Sans Limbu Regular" />
    <Font face-name="Noto Sans Lisu Regular" />
    <Font face-name="Noto Sans Malayalam UI Regular" />
    <Font face-name="Noto Sans Mandaic Regular" />
    <Font face-name="Noto Sans Mongolian Regular" />
    <Font face-name="Noto Sans Myanmar UI Regular" />
    <Font face-name="Noto Sans New Tai Lue Regular" />
    <Font face-name="Noto Sans NKo Regular" />
    <Font face-name="Noto Sans Ol Chiki Regular" />
    <Font face-name="Noto Sans Oriya UI Regular" />
    <Font face-name="Noto Sans Osage Regular" />
    <Font face-name="Noto Sans Osmanya Regular" />
    <Font face-name="Noto Sans Samaritan Regular" />
    <Font face-name="Noto Sans Saurashtra Regular" />
    <Font face-name="Noto Sans Shavian Regular" />
    <Font face-name="Noto Sans Sinhala UI Regular" />
    <Font face-name="Noto Sans Sinhala Regular" />
    <Font face-name="Noto Sans Sundanese Regular" />
    <Font face-name="Noto Sans Symbols Regular" />
    <Font face-name="Noto Sans Symbols2 Regular" />
    <Font face-name="Noto Sans Syriac Regular" />
    <Font face-name="Noto Sans Tagalog Regular" />
    <Font face-name="Noto Sans Tagbanwa Regular" />
    <Font face-name="Noto Sans Tai Le Regular" />
    <Font face-name="Noto Sans Tai Tham Regular" />
    <Font face-name="Noto Sans Tai Viet Regular" />
    <Font face-name="Noto Sans Tamil UI Regular" />
    <Font face-name="Noto Sans Telugu UI Regular" />
    <Font face-name="Noto Sans Thaana Regular" />
    <Font face-name="Noto Sans Thai UI Regular" />
    <Font face-name="Noto Sans Tifinagh Regular" />
    <Font face-name="Noto Sans Vai Regular" />
    <Font face-name="Noto Sans Yi Regular" />
    <Font face-name="Noto Sans Arabic UI Regular" />
    <Font face-name="Noto Naskh Arabic UI Regular" />
    <Font face-name="Noto Serif Tibetan Regular" />
    <Font face-name="Noto Emoji Regular" />
    <Font face-name="DejaVu Sans Book" />
    <Font face-name="HanaMinA Regular" />
    <Font face-name="HanaMinB Regular" />
    <Font face-name="Unifont Medium" />
  </FontSet>
  <Style name="drainage">
    <Rule>
      <Filter>([HYC]=8)</Filter>
      <PolygonSymbolizer fill="rgb(153,204,255)"/>
    </Rule>
  </Style>
  <Style name="highway-border">
    <Rule>
      <Filter>([CLASS]=1)</Filter>
      <LineSymbolizer stroke="rgb(188,149,28)" stroke-width="7" stroke-linejoin="round" stroke-linecap="round"/>
    </Rule>
  </Style>
  <Style name="highway-fill">
    <Rule>
      <Filter>([CLASS]=1)</Filter>
      <LineSymbolizer stroke="rgb(242,191,36)" stroke-width="5" stroke-linejoin="round" stroke-linecap="round"/>
    </Rule>
  </Style>
  <Style name="popplaces">
    <Rule>
      <TextSymbolizer face-name="DejaVu Sans Book" halo-radius="1" halo-fill="rgb(255,255,200)">[GEONAME]</TextSymbolizer>
    </Rule>
  </Style>
  <Style name="provinces">
    <Rule>
      <PolygonSymbolizer fill="rgb(17,235,203)"/>
    </Rule>
  </Style>
  <Style name="provlines">
    <Rule>
      <LineSymbolizer stroke="rgb(0,0,0)" stroke-width="1" stroke-dasharray="8,4,2,2,2,2"/>
    </Rule>
  </Style>
  <Style name="provlines_woods"/>
  <Style name="rest"/>
  <Style name="road-border">
    <Rule>
      <Filter>([CLASS]=2)</Filter>
      <LineSymbolizer stroke="rgb(171,158,137)" stroke-width="4" stroke-linejoin="round" stroke-linecap="round"/>
    </Rule>
  </Style>
  <Style name="road-fill">
    <Rule>
      <Filter>([CLASS]=2)</Filter>
      <LineSymbolizer stroke="rgb(255,250,115)" stroke-width="2" stroke-linejoin="round" stroke-linecap="round"/>
    </Rule>
  </Style>
  <Style name="smallroads">
    <Rule>
      <LineSymbolizer stroke="rgb(171,158,137)" stroke-width="2" stroke-linejoin="round" stroke-linecap="round"/>
    </Rule>
  </Style>
  <Layer name="Provinces" srs="+proj=lcc +ellps=GRS80 +lat_0=46.25 +lon_0=-63 +lat_1=46.8 +lat_2=47.7 +datum=NAD83 +units=m +no_defs">
    <StyleName>provinces</StyleName>
    <Datasource>
      <Parameter name="dbname">owm</Parameter>
      <Parameter name="host">postgres</Parameter>
      <Parameter name="password">toor</Parameter>
      <Parameter name="port">5432</Parameter>
      <Parameter name="table">planet_osm_polygon</Parameter>
      <Parameter name="type">postgis</Parameter>
      <Parameter name="user">owmuser</Parameter>
    </Datasource>
  </Layer>
  <Layer name="Provlines" srs="+proj=lcc +ellps=GRS80 +lat_0=46.25 +lon_0=-63 +lat_1=46.8 +lat_2=47.7 +datum=NAD83 +units=m +no_defs">
    <StyleName>provlines</StyleName>
    <Datasource>
      <Parameter name="dbname">owm</Parameter>
      <Parameter name="host">postgres</Parameter>
      <Parameter name="password">toor</Parameter>
      <Parameter name="port">5432</Parameter>
      <Parameter name="table">planet_osm_polygon</Parameter>
      <Parameter name="type">postgis</Parameter>
      <Parameter name="user">owmuser</Parameter>
    </Datasource>
  </Layer>
  <Layer name="Roads" srs="+proj=lcc +ellps=GRS80 +lat_0=46.25 +lon_0=-63 +lat_1=46.8 +lat_2=47.7 +datum=NAD83 +units=m +no_defs">
    <StyleName>smallroads</StyleName>
    <Datasource>
      <Parameter name="dbname">owm</Parameter>
      <Parameter name="host">postgres</Parameter>
      <Parameter name="password">toor</Parameter>
      <Parameter name="port">5432</Parameter>
      <Parameter name="table">planet_osm_roads</Parameter>
      <Parameter name="type">postgis</Parameter>
      <Parameter name="user">owmuser</Parameter>
    </Datasource>
  </Layer>
</Map>
